odoo/addons/l10n_ru/README.rst
odoo/addons/l10n_ru/__init__.py
odoo/addons/l10n_ru/__manifest__.py
odoo/addons/l10n_ru/data/account.account.template.csv
odoo/addons/l10n_ru/data/account_account_tag_data.xml
odoo/addons/l10n_ru/data/account_chart_template_configuration_data.xml
odoo/addons/l10n_ru/data/account_chart_template_data.xml
odoo/addons/l10n_ru/data/account_fiscal_position_template_data.xml
odoo/addons/l10n_ru/data/account_tax_group_data.xml
odoo/addons/l10n_ru/data/account_tax_report_line.xml
odoo/addons/l10n_ru/data/account_tax_template_data.xml
odoo/addons/l10n_ru/data/l10n_ru_chart_post_data.xml
odoo/addons/l10n_ru/i18n/l10n_ru.pot
odoo/addons/l10n_ru/readme/CONTRIBUTORS.rst
odoo/addons/l10n_ru/readme/DESCRIPTION.rst
odoo/addons/l10n_ru/static/description/account.png
odoo/addons/l10n_ru/static/description/icon.png
odoo/addons/l10n_ru/static/description/index.html
odoo14_addon_l10n_ru-14.0.1.0.1.dev1.dist-info/METADATA
odoo14_addon_l10n_ru-14.0.1.0.1.dev1.dist-info/WHEEL
odoo14_addon_l10n_ru-14.0.1.0.1.dev1.dist-info/top_level.txt
odoo14_addon_l10n_ru-14.0.1.0.1.dev1.dist-info/RECORD
