Metadata-Version: 2.1
Name: odoo14-addon-l10n-ru
Version: 14.0.1.0.1.dev1
Summary: Russia - Accounting
Home-page: https://github.com/OCA/l10n-russia
Author: CodUP, Katulos, Odoo Community Association (OCA)
Author-email: support@odoo-community.org
License: AGPL-3
Platform: UNKNOWN
Classifier: Programming Language :: Python
Classifier: Framework :: Odoo
Classifier: Framework :: Odoo :: 14.0
Classifier: License :: OSI Approved :: GNU Affero General Public License v3
Requires-Python: >=3.6
Requires-Dist: odoo <14.1dev,>=14.0a
